{
  "tasks": [
    {
      "id": "task-002",
      "title": "ConnectAI Social System (Airtable Build)",
      "status": "in-progress",
      "due": "2026-03-05",
      "agent": "Larrabee"
    }
  ],
  "approvals": [],
  "schedules": [
    {
      "id": "sched-001",
      "title": "Heartbeat Check",
      "time": "Every 30 minutes",
      "next": "2026-03-05T14:50:00Z"
    }
  ],
  "documents": [
    {
      "id": "doc-001",
      "title": "memory/2026-03-05.md",
      "generated": "2026-03-05T08:43:00Z"
    },
    {
      "id": "doc-002",
      "title": "mission-control/SETUP.md",
      "generated": "2026-03-05T09:35:00Z"
    },
    {
      "id": "doc-003",
      "title": "mission-control/UPDATE_STATE.md",
      "generated": "2026-03-05T09:35:00Z"
    },
    {
      "id": "doc-004",
      "title": "MEMORY.md (updated with Mission Control URL)",
      "generated": "2026-03-05T11:40:00Z"
    }
  ],
  "activity": [
    {
      "time": "14:20 UTC",
      "event": "ConnectAI: Stage 2 complete (Posts table with 33 fields + dummy data)",
      "type": "success"
    },
    {
      "time": "12:44 UTC",
      "event": "ConnectAI: Stage 3 automation instructions provided",
      "type": "update"
    },
    {
      "time": "12:14 UTC",
      "event": "ConnectAI: Stage 1 complete (Reference Image Library)",
      "type": "success"
    },
    {
      "time": "11:40 UTC",
      "event": "Corrected Mission Control URL in all documentation",
      "type": "update"
    }
  ],
  "_meta": {
    "lastUpdated": "2026-03-05T14:20:00Z",
    "version": "0.2.0"
  }
}
